{"id":"خصف","root":"خصف","rootLetters":["خ","ص","ف"],"meaning":"to sew, to patch","babs":[{"id":"خصف_I","form":"I","arabicPattern":"فَعَلَ","romanNumeral":"I","meaning":"Base form","color":"#4a9eff","tenses":[{"id":"خصف_I_mudari","type":"mudari","arabicName":"مُضَارِع","englishName":"Present (Muḍāriʿ)","color":"#00d4ff","occurrences":2,"references":["20:121","7:22"],"conjugation":[{"person":"3ms","arabic":"يَخْصُفُ","transliteration":"","english":"3rd masc. sg"},{"person":"3fs","arabic":"تَخْصُفُ","transliteration":"","english":"3rd fem. sg"},{"person":"3md","arabic":"يَخْصُفَانِ","transliteration":"","english":"3rd masc. dual"},{"person":"3fd","arabic":"تَخْصُفَانِ","transliteration":"","english":"3rd fem. dual"},{"person":"3mp","arabic":"يَخْصُفُونَ","transliteration":"","english":"3rd masc. pl"},{"person":"3fp","arabic":"يَخْصُفْنَ","transliteration":"","english":"3rd fem. pl"},{"person":"2ms","arabic":"تَخْصُفُ","transliteration":"","english":"2nd masc. sg"},{"person":"2fs","arabic":"تَخْصُفِينَ","transliteration":"","english":"2nd fem. sg"},{"person":"2md","arabic":"تَخْصُفَانِ","transliteration":"","english":"2nd masc. dual"},{"person":"2fd","arabic":"تَخْصُفَانِ","transliteration":"","english":"2nd fem. dual"},{"person":"2mp","arabic":"تَخْصُفُونَ","transliteration":"","english":"2nd masc. pl"},{"person":"2fp","arabic":"تَخْصُفْنَ","transliteration":"","english":"2nd fem. pl"},{"person":"1s","arabic":"أَخْصُفُ","transliteration":"","english":"1st singular"},{"person":"1p","arabic":"نَخْصُفُ","transliteration":"","english":"1st plural"}]}],"semanticMeaning":"Base form (Root meaning)","verbMeaning":"to sew, to patch together","masdar":"خَصْف","masdarNeedsApi":false,"faaeil":"خَاصِف","faaeilNeedsApi":true,"mafool":"مَخْصُوف","mafoolNeedsApi":true,"masdarAlternatives":[],"masdarDone":true}],"allReferences":["7:22","20:121"],"totalFreq":2}