{"id":"حوط","root":"حوط","rootLetters":["ح","و","ط"],"meaning":"to encompass, to protect","babs":[{"id":"حوط_IV","form":"IV","arabicPattern":"أَفْعَلَ","romanNumeral":"IV","meaning":"Causative","color":"#22c55e","tenses":[{"id":"حوط_IV_madi","type":"madi","arabicName":"مَاضِي","englishName":"Past (Māḍī)","color":"#ffd700","occurrences":8,"references":["17:60","18:29","18:91","27:22","2:81","48:21","65:12","72:28"],"conjugation":[{"person":"3ms","arabic":"أَحَاطَ","transliteration":"","english":"3rd masc. sg"},{"person":"3fs","arabic":"أَحَاطَتْ","transliteration":"","english":"3rd fem. sg"},{"person":"3md","arabic":"أَحَاطَا","transliteration":"","english":"3rd masc. dual"},{"person":"3fd","arabic":"أَحَاطَتَا","transliteration":"","english":"3rd fem. dual"},{"person":"3mp","arabic":"أَحَاطُوا","transliteration":"","english":"3rd masc. pl"},{"person":"3fp","arabic":"أَحَطْنَ","transliteration":"","english":"3rd fem. pl"},{"person":"2ms","arabic":"أَحَطْتَ","transliteration":"","english":"2nd masc. sg"},{"person":"2fs","arabic":"أَحَطْتِ","transliteration":"","english":"2nd fem. sg"},{"person":"2md","arabic":"أَحْوَطْتُمَا","transliteration":"","english":"2nd masc. dual"},{"person":"2fd","arabic":"أَحْوَطْتُمَا","transliteration":"","english":"2nd fem. dual"},{"person":"2mp","arabic":"أَحَطْتُمْ","transliteration":"","english":"2nd masc. pl"},{"person":"2fp","arabic":"أَحَطْتُنَّ","transliteration":"","english":"2nd fem. pl"},{"person":"1s","arabic":"أَحَطْتُ","transliteration":"","english":"1st singular"},{"person":"1p","arabic":"أَحَطْنَا","transliteration":"","english":"1st plural"}]},{"id":"حوط_IV_mudari","type":"mudari","arabicName":"مُضَارِع","englishName":"Present (Muḍāriʿ)","color":"#00d4ff","occurrences":6,"references":["10:39","18:68","20:110","27:22","27:84","2:255"],"conjugation":[{"person":"3ms","arabic":"يُحِيطُ","transliteration":"","english":"3rd masc. sg"},{"person":"3fs","arabic":"تُحِيطُ","transliteration":"","english":"3rd fem. sg"},{"person":"3md","arabic":"يُحِيطَانِ","transliteration":"","english":"3rd masc. dual"},{"person":"3fd","arabic":"تُحِيطَانِ","transliteration":"","english":"3rd fem. dual"},{"person":"3mp","arabic":"يُحِيطُونَ","transliteration":"","english":"3rd masc. pl"},{"person":"3fp","arabic":"يُحِطْنَ","transliteration":"","english":"3rd fem. pl"},{"person":"2ms","arabic":"تُحِيطُ","transliteration":"","english":"2nd masc. sg"},{"person":"2fs","arabic":"تُحِيطِينَ","transliteration":"","english":"2nd fem. sg"},{"person":"2md","arabic":"تُحْوِطَانِ","transliteration":"","english":"2nd masc. dual"},{"person":"2fd","arabic":"تُحْوِطَانِ","transliteration":"","english":"2nd fem. dual"},{"person":"2mp","arabic":"تُحِيطُونَ","transliteration":"","english":"2nd masc. pl"},{"person":"2fp","arabic":"تُحِطْنَ","transliteration":"","english":"2nd fem. pl"},{"person":"1s","arabic":"أُحِيطُ","transliteration":"","english":"1st singular"},{"person":"1p","arabic":"نُحِيطُ","transliteration":"","english":"1st plural"}]},{"id":"حوط_IV_passive_madi","type":"passive_madi","arabicName":"مَجْهُول مَاضِي","englishName":"Passive Past","color":"#c084fc","occurrences":2,"references":["10:22","18:42"],"conjugation":[{"person":"3ms","arabic":"أُحِيطَ","transliteration":"","english":"3rd masc. sg"},{"person":"3fs","arabic":"أُحِيطَتْ","transliteration":"","english":"3rd fem. sg"},{"person":"3md","arabic":"أُحِيطَا","transliteration":"","english":"3rd masc. dual"},{"person":"3fd","arabic":"أُحِيطَتَا","transliteration":"","english":"3rd fem. dual"},{"person":"3mp","arabic":"أُحِيطُوا","transliteration":"","english":"3rd masc. pl"},{"person":"3fp","arabic":"أُحِطْنَ","transliteration":"","english":"3rd fem. pl"},{"person":"2ms","arabic":"أُحِطْتَ","transliteration":"","english":"2nd masc. sg"},{"person":"2fs","arabic":"أُحِطْتِ","transliteration":"","english":"2nd fem. sg"},{"person":"2md","arabic":"أُحْوِطْتُمَا","transliteration":"","english":"2nd masc. dual"},{"person":"2fd","arabic":"أُحْوِطْتُمَا","transliteration":"","english":"2nd fem. dual"},{"person":"2mp","arabic":"أُحِطْتُمْ","transliteration":"","english":"2nd masc. pl"},{"person":"2fp","arabic":"أُحِطْتُنَّ","transliteration":"","english":"2nd fem. pl"},{"person":"1s","arabic":"أُحِطْتُ","transliteration":"","english":"1st singular"},{"person":"1p","arabic":"أُحِطْنَا","transliteration":"","english":"1st plural"}]},{"id":"حوط_IV_passive_mudari","type":"passive_mudari","arabicName":"مَجْهُول مُضَارِع","englishName":"Passive Present","color":"#86efac","occurrences":1,"references":["12:66"],"conjugation":[{"person":"3ms","arabic":"يُحَاطُ","transliteration":"","english":"3rd masc. sg"},{"person":"3fs","arabic":"تُحَاطُ","transliteration":"","english":"3rd fem. sg"},{"person":"3md","arabic":"يُحَاطَانِ","transliteration":"","english":"3rd masc. dual"},{"person":"3fd","arabic":"تُحَاطَانِ","transliteration":"","english":"3rd fem. dual"},{"person":"3mp","arabic":"يُحَاطُونَ","transliteration":"","english":"3rd masc. pl"},{"person":"3fp","arabic":"يُحَطْنَ","transliteration":"","english":"3rd fem. pl"},{"person":"2ms","arabic":"تُحَاطُ","transliteration":"","english":"2nd masc. sg"},{"person":"2fs","arabic":"تُحَاطِينَ","transliteration":"","english":"2nd fem. sg"},{"person":"2md","arabic":"تُحْوَطَانِ","transliteration":"","english":"2nd masc. dual"},{"person":"2fd","arabic":"تُحْوَطَانِ","transliteration":"","english":"2nd fem. dual"},{"person":"2mp","arabic":"تُحَاطُونَ","transliteration":"","english":"2nd masc. pl"},{"person":"2fp","arabic":"تُحَطْنَ","transliteration":"","english":"2nd fem. pl"},{"person":"1s","arabic":"أُحَاطُ","transliteration":"","english":"1st singular"},{"person":"1p","arabic":"نُحَاطُ","transliteration":"","english":"1st plural"}]}],"semanticMeaning":"Causative / Transitive","verbMeaning":"to encompass, to surround, to protect","masdar":"إِحَاطَة","masdarNeedsApi":false,"faaeil":"مُحِيط","faaeilNeedsApi":false,"mafool":"مُحَاط","mafoolNeedsApi":false,"derivationDone":true}],"allReferences":["2:19","2:81","2:255","3:120","4:108","4:126","8:47","9:49","10:22","10:39","11:84","11:92","12:66","17:60","18:29","18:42","18:68","18:91","20:110","27:22","27:84","29:54","41:54","48:21","65:12","72:28","85:20"],"totalFreq":28}