{"id":"شكو","root":"شكو","rootLetters":["ش","ك","و"],"meaning":"to complain, to lament","babs":[{"id":"شكو_I","form":"I","arabicPattern":"فَعَلَ","romanNumeral":"I","meaning":"Base form","color":"#4a9eff","tenses":[{"id":"شكو_I_mudari","type":"mudari","arabicName":"مُضَارِع","englishName":"Present (Muḍāriʿ)","color":"#00d4ff","occurrences":1,"references":["12:86"],"conjugation":[{"person":"3ms","arabic":"يَشْكُو","transliteration":"","english":"3rd masc. sg"},{"person":"3fs","arabic":"تَشْكُو","transliteration":"","english":"3rd fem. sg"},{"person":"3md","arabic":"يَشْكُيَانِ","transliteration":"","english":"3rd masc. dual"},{"person":"3fd","arabic":"تَشْكُيَانِ","transliteration":"","english":"3rd fem. dual"},{"person":"3mp","arabic":"يَشْكُونَ","transliteration":"","english":"3rd masc. pl"},{"person":"3fp","arabic":"يَشْكُونَ","transliteration":"","english":"3rd fem. pl"},{"person":"2ms","arabic":"تَشْكُو","transliteration":"","english":"2nd masc. sg"},{"person":"2fs","arabic":"تَشْكِينَ","transliteration":"","english":"2nd fem. sg"},{"person":"2md","arabic":"تَشْكُوَانِ","transliteration":"","english":"2nd masc. dual"},{"person":"2fd","arabic":"تَشْكُوَانِ","transliteration":"","english":"2nd fem. dual"},{"person":"2mp","arabic":"تَشْكُونَ","transliteration":"","english":"2nd masc. pl"},{"person":"2fp","arabic":"تَشْكُونَ","transliteration":"","english":"2nd fem. pl"},{"person":"1s","arabic":"أَشْكُو","transliteration":"","english":"1st singular"},{"person":"1p","arabic":"نَشْكُو","transliteration":"","english":"1st plural"}]}],"semanticMeaning":"Base form (Root meaning)","verbMeaning":"to complain, to express dissatisfaction","masdar":"شَكْوَى","masdarNeedsApi":false,"faaeil":"شَاكٍ","faaeilNeedsApi":false,"mafool":"مَشْكُوّ","mafoolNeedsApi":false,"masdarAlternatives":[],"masdarDone":true,"formIDerivDone":true},{"id":"شكو_VIII","form":"VIII","arabicPattern":"اِفْتَعَلَ","romanNumeral":"VIII","meaning":"Reflexive / middle","color":"#64748b","tenses":[{"id":"شكو_VIII_mudari","type":"mudari","arabicName":"مُضَارِع","englishName":"Present (Muḍāriʿ)","color":"#00d4ff","occurrences":1,"references":["58:1"],"conjugation":[{"person":"3ms","arabic":"يَشْتَكِي","transliteration":"","english":"3rd masc. sg"},{"person":"3fs","arabic":"تَشْتَكِي","transliteration":"","english":"3rd fem. sg"},{"person":"3md","arabic":"يَشْتَكِيَانِ","transliteration":"","english":"3rd masc. dual"},{"person":"3fd","arabic":"تَشْتَكِيَانِ","transliteration":"","english":"3rd fem. dual"},{"person":"3mp","arabic":"يَشْتَكُونَ","transliteration":"","english":"3rd masc. pl"},{"person":"3fp","arabic":"يَشْتَكِينَ","transliteration":"","english":"3rd fem. pl"},{"person":"2ms","arabic":"تَشْتَكِي","transliteration":"","english":"2nd masc. sg"},{"person":"2fs","arabic":"تَشْتَكِينَ","transliteration":"","english":"2nd fem. sg"},{"person":"2md","arabic":"تَشْتَكِوَانِ","transliteration":"","english":"2nd masc. dual"},{"person":"2fd","arabic":"تَشْتَكِوَانِ","transliteration":"","english":"2nd fem. dual"},{"person":"2mp","arabic":"تَشْتَكُونَ","transliteration":"","english":"2nd masc. pl"},{"person":"2fp","arabic":"تَشْتَكِينَ","transliteration":"","english":"2nd fem. pl"},{"person":"1s","arabic":"أَشْتَكِي","transliteration":"","english":"1st singular"},{"person":"1p","arabic":"نَشْتَكِي","transliteration":"","english":"1st plural"}]}],"semanticMeaning":"Reflexive / Intentional Effort","verbMeaning":"to complain vehemently, to lodge complaint","masdar":"اشْتِكَاء","masdarNeedsApi":false,"faaeil":"مُشْتَكٍ","faaeilNeedsApi":false,"mafool":"مُشْتَكًى","mafoolNeedsApi":false,"derivationDone":true}],"allReferences":["12:86","24:35","58:1"],"totalFreq":3}