{"id":"نشا","root":"نشا","rootLetters":["ن","ش","ا"],"meaning":"to grow, to arise, to originate","babs":[{"id":"نشا_II","form":"II","arabicPattern":"فَعَّلَ","romanNumeral":"II","meaning":"Intensive / causative","color":"#f97316","tenses":[{"id":"نشا_II_passive_mudari","type":"passive_mudari","arabicName":"مَجْهُول مُضَارِع","englishName":"Passive Present","color":"#86efac","occurrences":1,"references":["43:18"],"conjugation":[{"person":"3ms","arabic":"يُنَشَّى","transliteration":"","english":"3rd masc. sg"},{"person":"3fs","arabic":"تُنَشَّى","transliteration":"","english":"3rd fem. sg"},{"person":"3md","arabic":"يُنَشَّيَانِ","transliteration":"","english":"3rd masc. dual"},{"person":"3fd","arabic":"تُنَشَّيَانِ","transliteration":"","english":"3rd fem. dual"},{"person":"3mp","arabic":"يُنَشَّونَ","transliteration":"","english":"3rd masc. pl"},{"person":"3fp","arabic":"يُنَشَّينَ","transliteration":"","english":"3rd fem. pl"},{"person":"2ms","arabic":"تُنَشَّى","transliteration":"","english":"2nd masc. sg"},{"person":"2fs","arabic":"تُنَشَّينَ","transliteration":"","english":"2nd fem. sg"},{"person":"2md","arabic":"تُنَشَّاَانِ","transliteration":"","english":"2nd masc. dual"},{"person":"2fd","arabic":"تُنَشَّاَانِ","transliteration":"","english":"2nd fem. dual"},{"person":"2mp","arabic":"تُنَشَّونَ","transliteration":"","english":"2nd masc. pl"},{"person":"2fp","arabic":"تُنَشَّينَ","transliteration":"","english":"2nd fem. pl"},{"person":"1s","arabic":"أُنَشَّى","transliteration":"","english":"1st singular"},{"person":"1p","arabic":"نُنَشَّى","transliteration":"","english":"1st plural"}]}],"semanticMeaning":"Intensification / Causative","verbMeaning":"to raise, to bring up, to nurture","masdar":"تَنْشِيا","masdarNeedsApi":false,"faaeil":"مُنَشِّا","faaeilNeedsApi":false,"mafool":"مُنَشَّا","mafoolNeedsApi":false},{"id":"نشا_IV","form":"IV","arabicPattern":"أَفْعَلَ","romanNumeral":"IV","meaning":"Causative","color":"#22c55e","tenses":[{"id":"نشا_IV_madi","type":"madi","arabicName":"مَاضِي","englishName":"Past (Māḍī)","color":"#ffd700","occurrences":17,"references":["11:61","21:11","23:14","23:19","23:31","23:42","23:78","28:45"],"conjugation":[{"person":"3ms","arabic":"أَنْشَى","transliteration":"","english":"3rd masc. sg"},{"person":"3fs","arabic":"أَنْشَتْ","transliteration":"","english":"3rd fem. sg"},{"person":"3md","arabic":"أَنْشَيَا","transliteration":"","english":"3rd masc. dual"},{"person":"3fd","arabic":"أَنْشَتَا","transliteration":"","english":"3rd fem. dual"},{"person":"3mp","arabic":"أَنْشَوْا","transliteration":"","english":"3rd masc. pl"},{"person":"3fp","arabic":"أَنْشَيْنَ","transliteration":"","english":"3rd fem. pl"},{"person":"2ms","arabic":"أَنْشَيْتَ","transliteration":"","english":"2nd masc. sg"},{"person":"2fs","arabic":"أَنْشَيْتِ","transliteration":"","english":"2nd fem. sg"},{"person":"2md","arabic":"أَنْشَاْتُمَا","transliteration":"","english":"2nd masc. dual"},{"person":"2fd","arabic":"أَنْشَاْتُمَا","transliteration":"","english":"2nd fem. dual"},{"person":"2mp","arabic":"أَنْشَيْتُمْ","transliteration":"","english":"2nd masc. pl"},{"person":"2fp","arabic":"أَنْشَيْتُنَّ","transliteration":"","english":"2nd fem. pl"},{"person":"1s","arabic":"أَنْشَيْتُ","transliteration":"","english":"1st singular"},{"person":"1p","arabic":"أَنْشَيْنَا","transliteration":"","english":"1st plural"}]},{"id":"نشا_IV_mudari","type":"mudari","arabicName":"مُضَارِع","englishName":"Present (Muḍāriʿ)","color":"#00d4ff","occurrences":3,"references":["13:12","29:20","56:61"],"conjugation":[{"person":"3ms","arabic":"يُنْشِي","transliteration":"","english":"3rd masc. sg"},{"person":"3fs","arabic":"تُنْشِي","transliteration":"","english":"3rd fem. sg"},{"person":"3md","arabic":"يُنْشِيَانِ","transliteration":"","english":"3rd masc. dual"},{"person":"3fd","arabic":"تُنْشِيَانِ","transliteration":"","english":"3rd fem. dual"},{"person":"3mp","arabic":"يُنْشُونَ","transliteration":"","english":"3rd masc. pl"},{"person":"3fp","arabic":"يُنْشِينَ","transliteration":"","english":"3rd fem. pl"},{"person":"2ms","arabic":"تُنْشِي","transliteration":"","english":"2nd masc. sg"},{"person":"2fs","arabic":"تُنْشِينَ","transliteration":"","english":"2nd fem. sg"},{"person":"2md","arabic":"تُنْشِاَانِ","transliteration":"","english":"2nd masc. dual"},{"person":"2fd","arabic":"تُنْشِاَانِ","transliteration":"","english":"2nd fem. dual"},{"person":"2mp","arabic":"تُنْشُونَ","transliteration":"","english":"2nd masc. pl"},{"person":"2fp","arabic":"تُنْشِينَ","transliteration":"","english":"2nd fem. pl"},{"person":"1s","arabic":"أُنْشِي","transliteration":"","english":"1st singular"},{"person":"1p","arabic":"نُنْشِي","transliteration":"","english":"1st plural"}]}],"semanticMeaning":"Causative / Transitive","verbMeaning":"to produce, to originate, to create","masdar":"إِنْشَاا","masdarNeedsApi":false,"faaeil":"مُنْشِا","faaeilNeedsApi":false,"mafool":"مُنْشَا","mafoolNeedsApi":false}],"allReferences":["6:6","6:98","6:133","6:141","36:79","53:32","53:47","55:24","67:23","73:6"]}