{"id":"قرن","root":"قرن","rootLetters":["ق","ر","ن"],"meaning":"to pair, to couple","babs":[{"id":"قرن_I","form":"I","arabicPattern":"فَعَلَ","romanNumeral":"I","meaning":"Base form","color":"#4a9eff","masdar":"قَرْن","masdarNeedsApi":false,"faaeil":"قَارِن","faaeilNeedsApi":false,"mafool":"مَقْرُون","mafoolNeedsApi":false,"tenses":[{"id":"قرن_I_madi","type":"madi","arabicName":"مَاضِي","englishName":"Past (Māḍī)","color":"#ffd700","occurrences":0,"references":[],"conjugation":[{"person":"3ms","arabic":"قَرَنَ","transliteration":"","english":"3rd masc. sg"},{"person":"3fs","arabic":"قَرَنَتْ","transliteration":"","english":"3rd fem. sg"},{"person":"3md","arabic":"قَرَنَا","transliteration":"","english":"3rd masc. dual"},{"person":"3fd","arabic":"قَرَنَتَا","transliteration":"","english":"3rd fem. dual"},{"person":"3mp","arabic":"قَرَنُوا","transliteration":"","english":"3rd masc. pl"},{"person":"3fp","arabic":"قَرَنْنَ","transliteration":"","english":"3rd fem. pl"},{"person":"2ms","arabic":"قَرَنْتَ","transliteration":"","english":"2nd masc. sg"},{"person":"2fs","arabic":"قَرَنْتِ","transliteration":"","english":"2nd fem. sg"},{"person":"2md","arabic":"قَرَنْتُمَا","transliteration":"","english":"2nd masc. dual"},{"person":"2fd","arabic":"قَرَنْتُمَا","transliteration":"","english":"2nd fem. dual"},{"person":"2mp","arabic":"قَرَنْتُمْ","transliteration":"","english":"2nd masc. pl"},{"person":"2fp","arabic":"قَرَنْتُنَّ","transliteration":"","english":"2nd fem. pl"},{"person":"1s","arabic":"قَرَنْتُ","transliteration":"","english":"1st singular"},{"person":"1p","arabic":"قَرَنْنَا","transliteration":"","english":"1st plural"}]},{"id":"قرن_I_mudari","type":"mudari","arabicName":"مُضَارِع","englishName":"Present (Muḍāriʿ)","color":"#00d4ff","occurrences":0,"references":[],"conjugation":[{"person":"3ms","arabic":"يَقْرُنُ","transliteration":"","english":"3rd masc. sg"},{"person":"3fs","arabic":"تَقْرُنُ","transliteration":"","english":"3rd fem. sg"},{"person":"3md","arabic":"يَقْرُنَانِ","transliteration":"","english":"3rd masc. dual"},{"person":"3fd","arabic":"تَقْرُنَانِ","transliteration":"","english":"3rd fem. dual"},{"person":"3mp","arabic":"يَقْرُنُونَ","transliteration":"","english":"3rd masc. pl"},{"person":"3fp","arabic":"يَقْرُنْنَ","transliteration":"","english":"3rd fem. pl"},{"person":"2ms","arabic":"تَقْرُنُ","transliteration":"","english":"2nd masc. sg"},{"person":"2fs","arabic":"تَقْرُنِينَ","transliteration":"","english":"2nd fem. sg"},{"person":"2md","arabic":"تَقْرُنَانِ","transliteration":"","english":"2nd masc. dual"},{"person":"2fd","arabic":"تَقْرُنَانِ","transliteration":"","english":"2nd fem. dual"},{"person":"2mp","arabic":"تَقْرُنُونَ","transliteration":"","english":"2nd masc. pl"},{"person":"2fp","arabic":"تَقْرُنْنَ","transliteration":"","english":"2nd fem. pl"},{"person":"1s","arabic":"أَقْرُنُ","transliteration":"","english":"1st singular"},{"person":"1p","arabic":"نَقْرُنُ","transliteration":"","english":"1st plural"}]},{"id":"قرن_I_amr","type":"amr","arabicName":"أَمْر","englishName":"Imperative (Amr)","color":"#ff6b6b","occurrences":0,"references":[],"conjugation":[{"person":"2ms","arabic":"ٱُقْرُنْ","transliteration":"","english":"2nd masc. sg"},{"person":"2fs","arabic":"ٱُقْرُنِي","transliteration":"","english":"2nd fem. sg"},{"person":"2md","arabic":"ٱُقْرُنَا","transliteration":"","english":"2nd masc. dual"},{"person":"2fd","arabic":"ٱُقْرُنَا","transliteration":"","english":"2nd fem. dual"},{"person":"2mp","arabic":"ٱُقْرُنُوا","transliteration":"","english":"2nd masc. pl"},{"person":"2fp","arabic":"ٱُقْرُنْنَ","transliteration":"","english":"2nd fem. pl"}]},{"id":"قرن_I_passive_madi","type":"passive_madi","arabicName":"مَاضِي مَجْهُول","englishName":"Pass. Past","color":"#c084fc","occurrences":0,"references":[],"conjugation":[{"person":"3ms","arabic":"قُرِنَ","transliteration":"","english":"3rd masc. sg"},{"person":"3fs","arabic":"قُرِنَتْ","transliteration":"","english":"3rd fem. sg"},{"person":"3md","arabic":"قُرِنَا","transliteration":"","english":"3rd masc. dual"},{"person":"3fd","arabic":"قُرِنَتَا","transliteration":"","english":"3rd fem. dual"},{"person":"3mp","arabic":"قُرِنُوا","transliteration":"","english":"3rd masc. pl"},{"person":"3fp","arabic":"قُرِنْنَ","transliteration":"","english":"3rd fem. pl"},{"person":"2ms","arabic":"قُرِنْتَ","transliteration":"","english":"2nd masc. sg"},{"person":"2fs","arabic":"قُرِنْتِ","transliteration":"","english":"2nd fem. sg"},{"person":"2md","arabic":"قُرِنْتُمَا","transliteration":"","english":"2nd masc. dual"},{"person":"2fd","arabic":"قُرِنْتُمَا","transliteration":"","english":"2nd fem. dual"},{"person":"2mp","arabic":"قُرِنْتُمْ","transliteration":"","english":"2nd masc. pl"},{"person":"2fp","arabic":"قُرِنْتُنَّ","transliteration":"","english":"2nd fem. pl"},{"person":"1s","arabic":"قُرِنْتُ","transliteration":"","english":"1st singular"},{"person":"1p","arabic":"قُرِنْنَا","transliteration":"","english":"1st plural"}]},{"id":"قرن_I_passive_mudari","type":"passive_mudari","arabicName":"مُضَارِع مَجْهُول","englishName":"Pass. Present","color":"#86efac","occurrences":0,"references":[],"conjugation":[{"person":"3ms","arabic":"يُقْرَنُ","transliteration":"","english":"3rd masc. sg"},{"person":"3fs","arabic":"تُقْرَنُ","transliteration":"","english":"3rd fem. sg"},{"person":"3md","arabic":"يُقْرَنَانِ","transliteration":"","english":"3rd masc. dual"},{"person":"3fd","arabic":"تُقْرَنَانِ","transliteration":"","english":"3rd fem. dual"},{"person":"3mp","arabic":"يُقْرَنُونَ","transliteration":"","english":"3rd masc. pl"},{"person":"3fp","arabic":"يُقْرَنْنَ","transliteration":"","english":"3rd fem. pl"},{"person":"2ms","arabic":"تُقْرَنُ","transliteration":"","english":"2nd masc. sg"},{"person":"2fs","arabic":"تُقْرَنِينَ","transliteration":"","english":"2nd fem. sg"},{"person":"2md","arabic":"تُقْرَنَانِ","transliteration":"","english":"2nd masc. dual"},{"person":"2fd","arabic":"تُقْرَنَانِ","transliteration":"","english":"2nd fem. dual"},{"person":"2mp","arabic":"تُقْرَنُونَ","transliteration":"","english":"2nd masc. pl"},{"person":"2fp","arabic":"تُقْرَنْنَ","transliteration":"","english":"2nd fem. pl"},{"person":"1s","arabic":"أُقْرَنُ","transliteration":"","english":"1st singular"},{"person":"1p","arabic":"نُقْرَنُ","transliteration":"","english":"1st plural"}]}]},{"id":"قرن_II","form":"II","arabicPattern":"","romanNumeral":"II","meaning":"Intensification / Causative","color":"#f97316","masdar":"تَقْرِين","masdarNeedsApi":false,"faaeil":"مُقَرِّن","faaeilNeedsApi":false,"mafool":"مُقَرَّن","mafoolNeedsApi":false,"tenses":[{"id":"قرن_II_madi","type":"madi","arabicName":"مَاضِي","englishName":"Past (Māḍī)","color":"#ffd700","occurrences":0,"references":[],"conjugation":[{"person":"3ms","arabic":"قَرَّنَ","transliteration":"","english":"3rd masc. sg"},{"person":"3fs","arabic":"قَرَّنَتْ","transliteration":"","english":"3rd fem. sg"},{"person":"3md","arabic":"قَرَّنَا","transliteration":"","english":"3rd masc. dual"},{"person":"3fd","arabic":"قَرَّنَتَا","transliteration":"","english":"3rd fem. dual"},{"person":"3mp","arabic":"قَرَّنُوا","transliteration":"","english":"3rd masc. pl"},{"person":"3fp","arabic":"قَرَّنْنَ","transliteration":"","english":"3rd fem. pl"},{"person":"2ms","arabic":"قَرَّنْتَ","transliteration":"","english":"2nd masc. sg"},{"person":"2fs","arabic":"قَرَّنْتِ","transliteration":"","english":"2nd fem. sg"},{"person":"2md","arabic":"قَرَّنْتُمَا","transliteration":"","english":"2nd masc. dual"},{"person":"2fd","arabic":"قَرَّنْتُمَا","transliteration":"","english":"2nd fem. dual"},{"person":"2mp","arabic":"قَرَّنْتُمْ","transliteration":"","english":"2nd masc. pl"},{"person":"2fp","arabic":"قَرَّنْتُنَّ","transliteration":"","english":"2nd fem. pl"},{"person":"1s","arabic":"قَرَّنْتُ","transliteration":"","english":"1st singular"},{"person":"1p","arabic":"قَرَّنْنَا","transliteration":"","english":"1st plural"}]},{"id":"قرن_II_mudari","type":"mudari","arabicName":"مُضَارِع","englishName":"Present (Muḍāriʿ)","color":"#00d4ff","occurrences":0,"references":[],"conjugation":[{"person":"3ms","arabic":"يَقَرِّنُ","transliteration":"","english":"3rd masc. sg"},{"person":"3fs","arabic":"تَقَرِّنُ","transliteration":"","english":"3rd fem. sg"},{"person":"3md","arabic":"يَقَرِّنَانِ","transliteration":"","english":"3rd masc. dual"},{"person":"3fd","arabic":"تَقَرِّنَانِ","transliteration":"","english":"3rd fem. dual"},{"person":"3mp","arabic":"يَقَرِّنُونَ","transliteration":"","english":"3rd masc. pl"},{"person":"3fp","arabic":"يَقَرِّنْنَ","transliteration":"","english":"3rd fem. pl"},{"person":"2ms","arabic":"تَقَرِّنُ","transliteration":"","english":"2nd masc. sg"},{"person":"2fs","arabic":"تَقَرِّنِينَ","transliteration":"","english":"2nd fem. sg"},{"person":"2md","arabic":"تَقَرِّنَانِ","transliteration":"","english":"2nd masc. dual"},{"person":"2fd","arabic":"تَقَرِّنَانِ","transliteration":"","english":"2nd fem. dual"},{"person":"2mp","arabic":"تَقَرِّنُونَ","transliteration":"","english":"2nd masc. pl"},{"person":"2fp","arabic":"تَقَرِّنْنَ","transliteration":"","english":"2nd fem. pl"},{"person":"1s","arabic":"أَقَرِّنُ","transliteration":"","english":"1st singular"},{"person":"1p","arabic":"نَقَرِّنُ","transliteration":"","english":"1st plural"}]},{"id":"قرن_II_amr","type":"amr","arabicName":"أَمْر","englishName":"Imperative (Amr)","color":"#ff6b6b","occurrences":0,"references":[],"conjugation":[{"person":"2ms","arabic":"قَرِّنْ","transliteration":"","english":"2nd masc. sg"},{"person":"2fs","arabic":"قَرِّنِي","transliteration":"","english":"2nd fem. sg"},{"person":"2md","arabic":"قَرِّنَا","transliteration":"","english":"2nd masc. dual"},{"person":"2fd","arabic":"قَرِّنَا","transliteration":"","english":"2nd fem. dual"},{"person":"2mp","arabic":"قَرِّنُوا","transliteration":"","english":"2nd masc. pl"},{"person":"2fp","arabic":"قَرِّنْنَ","transliteration":"","english":"2nd fem. pl"}]},{"id":"قرن_II_passive_madi","type":"passive_madi","arabicName":"مَاضِي مَجْهُول","englishName":"Pass. Past","color":"#c084fc","occurrences":0,"references":[],"conjugation":[{"person":"3ms","arabic":"قُرِّنَ","transliteration":"","english":"3rd masc. sg"},{"person":"3fs","arabic":"قُرِّنَتْ","transliteration":"","english":"3rd fem. sg"},{"person":"3md","arabic":"قُرِّنَا","transliteration":"","english":"3rd masc. dual"},{"person":"3fd","arabic":"قُرِّنَتَا","transliteration":"","english":"3rd fem. dual"},{"person":"3mp","arabic":"قُرِّنُوا","transliteration":"","english":"3rd masc. pl"},{"person":"3fp","arabic":"قُرِّنْنَ","transliteration":"","english":"3rd fem. pl"},{"person":"2ms","arabic":"قُرِّنْتَ","transliteration":"","english":"2nd masc. sg"},{"person":"2fs","arabic":"قُرِّنْتِ","transliteration":"","english":"2nd fem. sg"},{"person":"2md","arabic":"قُرِّنْتُمَا","transliteration":"","english":"2nd masc. dual"},{"person":"2fd","arabic":"قُرِّنْتُمَا","transliteration":"","english":"2nd fem. dual"},{"person":"2mp","arabic":"قُرِّنْتُمْ","transliteration":"","english":"2nd masc. pl"},{"person":"2fp","arabic":"قُرِّنْتُنَّ","transliteration":"","english":"2nd fem. pl"},{"person":"1s","arabic":"قُرِّنْتُ","transliteration":"","english":"1st singular"},{"person":"1p","arabic":"قُرِّنْنَا","transliteration":"","english":"1st plural"}]},{"id":"قرن_II_passive_mudari","type":"passive_mudari","arabicName":"مُضَارِع مَجْهُول","englishName":"Pass. Present","color":"#86efac","occurrences":0,"references":[],"conjugation":[{"person":"3ms","arabic":"يُقَرَّنُ","transliteration":"","english":"3rd masc. sg"},{"person":"3fs","arabic":"تُقَرَّنُ","transliteration":"","english":"3rd fem. sg"},{"person":"3md","arabic":"يُقَرَّنَانِ","transliteration":"","english":"3rd masc. dual"},{"person":"3fd","arabic":"تُقَرَّنَانِ","transliteration":"","english":"3rd fem. dual"},{"person":"3mp","arabic":"يُقَرَّنُونَ","transliteration":"","english":"3rd masc. pl"},{"person":"3fp","arabic":"يُقَرَّنْنَ","transliteration":"","english":"3rd fem. pl"},{"person":"2ms","arabic":"تُقَرَّنُ","transliteration":"","english":"2nd masc. sg"},{"person":"2fs","arabic":"تُقَرَّنِينَ","transliteration":"","english":"2nd fem. sg"},{"person":"2md","arabic":"تُقَرَّنَانِ","transliteration":"","english":"2nd masc. dual"},{"person":"2fd","arabic":"تُقَرَّنَانِ","transliteration":"","english":"2nd fem. dual"},{"person":"2mp","arabic":"تُقَرَّنُونَ","transliteration":"","english":"2nd masc. pl"},{"person":"2fp","arabic":"تُقَرَّنْنَ","transliteration":"","english":"2nd fem. pl"},{"person":"1s","arabic":"أُقَرَّنُ","transliteration":"","english":"1st singular"},{"person":"1p","arabic":"نُقَرَّنُ","transliteration":"","english":"1st plural"}]}],"derivationDone":true},{"id":"قرن_III","form":"III","arabicPattern":"","romanNumeral":"III","meaning":"Mutual Action","color":"#a855f7","masdar":"قِرَان","masdarNeedsApi":false,"faaeil":"قَارِن","faaeilNeedsApi":false,"mafool":"مُقَارَن","mafoolNeedsApi":false,"tenses":[{"id":"قرن_III_madi","type":"madi","arabicName":"مَاضِي","englishName":"Past (Māḍī)","color":"#ffd700","occurrences":0,"references":[],"conjugation":[{"person":"3ms","arabic":"قَارَنَ","transliteration":"","english":"3rd masc. sg"},{"person":"3fs","arabic":"قَارَنَتْ","transliteration":"","english":"3rd fem. sg"},{"person":"3md","arabic":"قَارَنَا","transliteration":"","english":"3rd masc. dual"},{"person":"3fd","arabic":"قَارَنَتَا","transliteration":"","english":"3rd fem. dual"},{"person":"3mp","arabic":"قَارَنُوا","transliteration":"","english":"3rd masc. pl"},{"person":"3fp","arabic":"قَارَنْنَ","transliteration":"","english":"3rd fem. pl"},{"person":"2ms","arabic":"قَارَنْتَ","transliteration":"","english":"2nd masc. sg"},{"person":"2fs","arabic":"قَارَنْتِ","transliteration":"","english":"2nd fem. sg"},{"person":"2md","arabic":"قَارَنْتُمَا","transliteration":"","english":"2nd masc. dual"},{"person":"2fd","arabic":"قَارَنْتُمَا","transliteration":"","english":"2nd fem. dual"},{"person":"2mp","arabic":"قَارَنْتُمْ","transliteration":"","english":"2nd masc. pl"},{"person":"2fp","arabic":"قَارَنْتُنَّ","transliteration":"","english":"2nd fem. pl"},{"person":"1s","arabic":"قَارَنْتُ","transliteration":"","english":"1st singular"},{"person":"1p","arabic":"قَارَنْنَا","transliteration":"","english":"1st plural"}]},{"id":"قرن_III_mudari","type":"mudari","arabicName":"مُضَارِع","englishName":"Present (Muḍāriʿ)","color":"#00d4ff","occurrences":0,"references":[],"conjugation":[{"person":"3ms","arabic":"يَقَارِنُ","transliteration":"","english":"3rd masc. sg"},{"person":"3fs","arabic":"تَقَارِنُ","transliteration":"","english":"3rd fem. sg"},{"person":"3md","arabic":"يَقَارِنَانِ","transliteration":"","english":"3rd masc. dual"},{"person":"3fd","arabic":"تَقَارِنَانِ","transliteration":"","english":"3rd fem. dual"},{"person":"3mp","arabic":"يَقَارِنُونَ","transliteration":"","english":"3rd masc. pl"},{"person":"3fp","arabic":"يَقَارِنْنَ","transliteration":"","english":"3rd fem. pl"},{"person":"2ms","arabic":"تَقَارِنُ","transliteration":"","english":"2nd masc. sg"},{"person":"2fs","arabic":"تَقَارِنِينَ","transliteration":"","english":"2nd fem. sg"},{"person":"2md","arabic":"تَقَارِنَانِ","transliteration":"","english":"2nd masc. dual"},{"person":"2fd","arabic":"تَقَارِنَانِ","transliteration":"","english":"2nd fem. dual"},{"person":"2mp","arabic":"تَقَارِنُونَ","transliteration":"","english":"2nd masc. pl"},{"person":"2fp","arabic":"تَقَارِنْنَ","transliteration":"","english":"2nd fem. pl"},{"person":"1s","arabic":"أَقَارِنُ","transliteration":"","english":"1st singular"},{"person":"1p","arabic":"نَقَارِنُ","transliteration":"","english":"1st plural"}]},{"id":"قرن_III_amr","type":"amr","arabicName":"أَمْر","englishName":"Imperative (Amr)","color":"#ff6b6b","occurrences":0,"references":[],"conjugation":[{"person":"2ms","arabic":"قَارِنْ","transliteration":"","english":"2nd masc. sg"},{"person":"2fs","arabic":"قَارِنِي","transliteration":"","english":"2nd fem. sg"},{"person":"2md","arabic":"قَارِنَا","transliteration":"","english":"2nd masc. dual"},{"person":"2fd","arabic":"قَارِنَا","transliteration":"","english":"2nd fem. dual"},{"person":"2mp","arabic":"قَارِنُوا","transliteration":"","english":"2nd masc. pl"},{"person":"2fp","arabic":"قَارِنْنَ","transliteration":"","english":"2nd fem. pl"}]},{"id":"قرن_III_passive_madi","type":"passive_madi","arabicName":"مَاضِي مَجْهُول","englishName":"Pass. Past","color":"#c084fc","occurrences":0,"references":[],"conjugation":[{"person":"3ms","arabic":"قُورِنَ","transliteration":"","english":"3rd masc. sg"},{"person":"3fs","arabic":"قُورِنَتْ","transliteration":"","english":"3rd fem. sg"},{"person":"3md","arabic":"قُورِنَا","transliteration":"","english":"3rd masc. dual"},{"person":"3fd","arabic":"قُورِنَتَا","transliteration":"","english":"3rd fem. dual"},{"person":"3mp","arabic":"قُورِنُوا","transliteration":"","english":"3rd masc. pl"},{"person":"3fp","arabic":"قُورِنْنَ","transliteration":"","english":"3rd fem. pl"},{"person":"2ms","arabic":"قُورِنْتَ","transliteration":"","english":"2nd masc. sg"},{"person":"2fs","arabic":"قُورِنْتِ","transliteration":"","english":"2nd fem. sg"},{"person":"2md","arabic":"قُورِنْتُمَا","transliteration":"","english":"2nd masc. dual"},{"person":"2fd","arabic":"قُورِنْتُمَا","transliteration":"","english":"2nd fem. dual"},{"person":"2mp","arabic":"قُورِنْتُمْ","transliteration":"","english":"2nd masc. pl"},{"person":"2fp","arabic":"قُورِنْتُنَّ","transliteration":"","english":"2nd fem. pl"},{"person":"1s","arabic":"قُورِنْتُ","transliteration":"","english":"1st singular"},{"person":"1p","arabic":"قُورِنْنَا","transliteration":"","english":"1st plural"}]},{"id":"قرن_III_passive_mudari","type":"passive_mudari","arabicName":"مُضَارِع مَجْهُول","englishName":"Pass. Present","color":"#86efac","occurrences":0,"references":[],"conjugation":[{"person":"3ms","arabic":"يُقَارَنُ","transliteration":"","english":"3rd masc. sg"},{"person":"3fs","arabic":"تُقَارَنُ","transliteration":"","english":"3rd fem. sg"},{"person":"3md","arabic":"يُقَارَنَانِ","transliteration":"","english":"3rd masc. dual"},{"person":"3fd","arabic":"تُقَارَنَانِ","transliteration":"","english":"3rd fem. dual"},{"person":"3mp","arabic":"يُقَارَنُونَ","transliteration":"","english":"3rd masc. pl"},{"person":"3fp","arabic":"يُقَارَنْنَ","transliteration":"","english":"3rd fem. pl"},{"person":"2ms","arabic":"تُقَارَنُ","transliteration":"","english":"2nd masc. sg"},{"person":"2fs","arabic":"تُقَارَنِينَ","transliteration":"","english":"2nd fem. sg"},{"person":"2md","arabic":"تُقَارَنَانِ","transliteration":"","english":"2nd masc. dual"},{"person":"2fd","arabic":"تُقَارَنَانِ","transliteration":"","english":"2nd fem. dual"},{"person":"2mp","arabic":"تُقَارَنُونَ","transliteration":"","english":"2nd masc. pl"},{"person":"2fp","arabic":"تُقَارَنْنَ","transliteration":"","english":"2nd fem. pl"},{"person":"1s","arabic":"أُقَارَنُ","transliteration":"","english":"1st singular"},{"person":"1p","arabic":"نُقَارَنُ","transliteration":"","english":"1st plural"}]}],"derivationDone":true},{"id":"قرن_IV","form":"IV","arabicPattern":"","romanNumeral":"IV","meaning":"Causative / Transitive","color":"#22c55e","masdar":"إِقْرَان","masdarNeedsApi":false,"faaeil":"مُقْرِن","faaeilNeedsApi":false,"mafool":"مُقْرَان","mafoolNeedsApi":false,"tenses":[{"id":"قرن_IV_madi","type":"madi","arabicName":"مَاضِي","englishName":"Past (Māḍī)","color":"#ffd700","occurrences":0,"references":[],"conjugation":[{"person":"3ms","arabic":"أَقْرَنَ","transliteration":"","english":"3rd masc. sg"},{"person":"3fs","arabic":"أَقْرَنَتْ","transliteration":"","english":"3rd fem. sg"},{"person":"3md","arabic":"أَقْرَنَا","transliteration":"","english":"3rd masc. dual"},{"person":"3fd","arabic":"أَقْرَنَتَا","transliteration":"","english":"3rd fem. dual"},{"person":"3mp","arabic":"أَقْرَنُوا","transliteration":"","english":"3rd masc. pl"},{"person":"3fp","arabic":"أَقْرَنْنَ","transliteration":"","english":"3rd fem. pl"},{"person":"2ms","arabic":"أَقْرَنْتَ","transliteration":"","english":"2nd masc. sg"},{"person":"2fs","arabic":"أَقْرَنْتِ","transliteration":"","english":"2nd fem. sg"},{"person":"2md","arabic":"أَقْرَنْتُمَا","transliteration":"","english":"2nd masc. dual"},{"person":"2fd","arabic":"أَقْرَنْتُمَا","transliteration":"","english":"2nd fem. dual"},{"person":"2mp","arabic":"أَقْرَنْتُمْ","transliteration":"","english":"2nd masc. pl"},{"person":"2fp","arabic":"أَقْرَنْتُنَّ","transliteration":"","english":"2nd fem. pl"},{"person":"1s","arabic":"أَقْرَنْتُ","transliteration":"","english":"1st singular"},{"person":"1p","arabic":"أَقْرَنْنَا","transliteration":"","english":"1st plural"}]},{"id":"قرن_IV_mudari","type":"mudari","arabicName":"مُضَارِع","englishName":"Present (Muḍāriʿ)","color":"#00d4ff","occurrences":0,"references":[],"conjugation":[{"person":"3ms","arabic":"يُقْرِنُ","transliteration":"","english":"3rd masc. sg"},{"person":"3fs","arabic":"تُقْرِنُ","transliteration":"","english":"3rd fem. sg"},{"person":"3md","arabic":"يُقْرِنَانِ","transliteration":"","english":"3rd masc. dual"},{"person":"3fd","arabic":"تُقْرِنَانِ","transliteration":"","english":"3rd fem. dual"},{"person":"3mp","arabic":"يُقْرِنُونَ","transliteration":"","english":"3rd masc. pl"},{"person":"3fp","arabic":"يُقْرِنْنَ","transliteration":"","english":"3rd fem. pl"},{"person":"2ms","arabic":"تُقْرِنُ","transliteration":"","english":"2nd masc. sg"},{"person":"2fs","arabic":"تُقْرِنِينَ","transliteration":"","english":"2nd fem. sg"},{"person":"2md","arabic":"تُقْرِنَانِ","transliteration":"","english":"2nd masc. dual"},{"person":"2fd","arabic":"تُقْرِنَانِ","transliteration":"","english":"2nd fem. dual"},{"person":"2mp","arabic":"تُقْرِنُونَ","transliteration":"","english":"2nd masc. pl"},{"person":"2fp","arabic":"تُقْرِنْنَ","transliteration":"","english":"2nd fem. pl"},{"person":"1s","arabic":"أُقْرِنُ","transliteration":"","english":"1st singular"},{"person":"1p","arabic":"نُقْرِنُ","transliteration":"","english":"1st plural"}]},{"id":"قرن_IV_amr","type":"amr","arabicName":"أَمْر","englishName":"Imperative (Amr)","color":"#ff6b6b","occurrences":0,"references":[],"conjugation":[{"person":"2ms","arabic":"أَقْرِنْ","transliteration":"","english":"2nd masc. sg"},{"person":"2fs","arabic":"أَقْرِنِي","transliteration":"","english":"2nd fem. sg"},{"person":"2md","arabic":"أَقْرِنَا","transliteration":"","english":"2nd masc. dual"},{"person":"2fd","arabic":"أَقْرِنَا","transliteration":"","english":"2nd fem. dual"},{"person":"2mp","arabic":"أَقْرِنُوا","transliteration":"","english":"2nd masc. pl"},{"person":"2fp","arabic":"أَقْرِنْنَ","transliteration":"","english":"2nd fem. pl"}]},{"id":"قرن_IV_passive_madi","type":"passive_madi","arabicName":"مَاضِي مَجْهُول","englishName":"Pass. Past","color":"#c084fc","occurrences":0,"references":[],"conjugation":[{"person":"3ms","arabic":"أُقْرِنَ","transliteration":"","english":"3rd masc. sg"},{"person":"3fs","arabic":"أُقْرِنَتْ","transliteration":"","english":"3rd fem. sg"},{"person":"3md","arabic":"أُقْرِنَا","transliteration":"","english":"3rd masc. dual"},{"person":"3fd","arabic":"أُقْرِنَتَا","transliteration":"","english":"3rd fem. dual"},{"person":"3mp","arabic":"أُقْرِنُوا","transliteration":"","english":"3rd masc. pl"},{"person":"3fp","arabic":"أُقْرِنْنَ","transliteration":"","english":"3rd fem. pl"},{"person":"2ms","arabic":"أُقْرِنْتَ","transliteration":"","english":"2nd masc. sg"},{"person":"2fs","arabic":"أُقْرِنْتِ","transliteration":"","english":"2nd fem. sg"},{"person":"2md","arabic":"أُقْرِنْتُمَا","transliteration":"","english":"2nd masc. dual"},{"person":"2fd","arabic":"أُقْرِنْتُمَا","transliteration":"","english":"2nd fem. dual"},{"person":"2mp","arabic":"أُقْرِنْتُمْ","transliteration":"","english":"2nd masc. pl"},{"person":"2fp","arabic":"أُقْرِنْتُنَّ","transliteration":"","english":"2nd fem. pl"},{"person":"1s","arabic":"أُقْرِنْتُ","transliteration":"","english":"1st singular"},{"person":"1p","arabic":"أُقْرِنْنَا","transliteration":"","english":"1st plural"}]},{"id":"قرن_IV_passive_mudari","type":"passive_mudari","arabicName":"مُضَارِع مَجْهُول","englishName":"Pass. Present","color":"#86efac","occurrences":0,"references":[],"conjugation":[{"person":"3ms","arabic":"يُقْرَنُ","transliteration":"","english":"3rd masc. sg"},{"person":"3fs","arabic":"تُقْرَنُ","transliteration":"","english":"3rd fem. sg"},{"person":"3md","arabic":"يُقْرَنَانِ","transliteration":"","english":"3rd masc. dual"},{"person":"3fd","arabic":"تُقْرَنَانِ","transliteration":"","english":"3rd fem. dual"},{"person":"3mp","arabic":"يُقْرَنُونَ","transliteration":"","english":"3rd masc. pl"},{"person":"3fp","arabic":"يُقْرَنْنَ","transliteration":"","english":"3rd fem. pl"},{"person":"2ms","arabic":"تُقْرَنُ","transliteration":"","english":"2nd masc. sg"},{"person":"2fs","arabic":"تُقْرَنِينَ","transliteration":"","english":"2nd fem. sg"},{"person":"2md","arabic":"تُقْرَنَانِ","transliteration":"","english":"2nd masc. dual"},{"person":"2fd","arabic":"تُقْرَنَانِ","transliteration":"","english":"2nd fem. dual"},{"person":"2mp","arabic":"تُقْرَنُونَ","transliteration":"","english":"2nd masc. pl"},{"person":"2fp","arabic":"تُقْرَنْنَ","transliteration":"","english":"2nd fem. pl"},{"person":"1s","arabic":"أُقْرَنُ","transliteration":"","english":"1st singular"},{"person":"1p","arabic":"نُقْرَنُ","transliteration":"","english":"1st plural"}]}],"derivationDone":true}],"totalFreq":33,"enriched":false,"allReferences":["4:38","6:6","10:13","11:116","14:49","17:17","19:74","19:98","20:51","20:128","23:31","23:42","25:13","25:38","28:43","28:45","28:78","32:26","36:31","37:51","38:3","38:38","41:25","43:13","43:36","43:38","43:53","46:17","50:23","50:27","50:36"],"validationDone":true,"isVerb":true}