{"id":"وصد","root":"وصد","rootLetters":["و","ص","د"],"meaning":"to close; to block","babs":[{"id":"وصد_I","form":"I","arabicPattern":"فَعَلَ","romanNumeral":"I","meaning":"Base form","color":"#4a9eff","masdar":"وَصْد","masdarNeedsApi":false,"faaeil":"وَاصِد","faaeilNeedsApi":false,"mafool":"مَوْصُود","mafoolNeedsApi":false,"tenses":[{"id":"وصد_I_madi","type":"madi","arabicName":"مَاضِي","englishName":"Past (Māḍī)","color":"#ffd700","occurrences":0,"references":[],"conjugation":[{"person":"3ms","arabic":"وَصَدَ","transliteration":"","english":"3rd masc. sg"},{"person":"3fs","arabic":"وَصَدَتْ","transliteration":"","english":"3rd fem. sg"},{"person":"3md","arabic":"وَصَدَا","transliteration":"","english":"3rd masc. dual"},{"person":"3fd","arabic":"وَصَدَتَا","transliteration":"","english":"3rd fem. dual"},{"person":"3mp","arabic":"وَصَدُوا","transliteration":"","english":"3rd masc. pl"},{"person":"3fp","arabic":"وَصَدْنَ","transliteration":"","english":"3rd fem. pl"},{"person":"2ms","arabic":"وَصَدْتَ","transliteration":"","english":"2nd masc. sg"},{"person":"2fs","arabic":"وَصَدْتِ","transliteration":"","english":"2nd fem. sg"},{"person":"2md","arabic":"وَصَدْتُمَا","transliteration":"","english":"2nd masc. dual"},{"person":"2fd","arabic":"وَصَدْتُمَا","transliteration":"","english":"2nd fem. dual"},{"person":"2mp","arabic":"وَصَدْتُمْ","transliteration":"","english":"2nd masc. pl"},{"person":"2fp","arabic":"وَصَدْتُنَّ","transliteration":"","english":"2nd fem. pl"},{"person":"1s","arabic":"وَصَدْتُ","transliteration":"","english":"1st singular"},{"person":"1p","arabic":"وَصَدْنَا","transliteration":"","english":"1st plural"}]},{"id":"وصد_I_mudari","type":"mudari","arabicName":"مُضَارِع","englishName":"Present (Muḍāriʿ)","color":"#00d4ff","occurrences":0,"references":[],"conjugation":[{"person":"3ms","arabic":"يَوْصُدُ","transliteration":"","english":"3rd masc. sg"},{"person":"3fs","arabic":"تَوْصُدُ","transliteration":"","english":"3rd fem. sg"},{"person":"3md","arabic":"يَوْصُدَانِ","transliteration":"","english":"3rd masc. dual"},{"person":"3fd","arabic":"تَوْصُدَانِ","transliteration":"","english":"3rd fem. dual"},{"person":"3mp","arabic":"يَوْصُدُونَ","transliteration":"","english":"3rd masc. pl"},{"person":"3fp","arabic":"يَوْصُدْنَ","transliteration":"","english":"3rd fem. pl"},{"person":"2ms","arabic":"تَوْصُدُ","transliteration":"","english":"2nd masc. sg"},{"person":"2fs","arabic":"تَوْصُدِينَ","transliteration":"","english":"2nd fem. sg"},{"person":"2md","arabic":"تَوْصُدَانِ","transliteration":"","english":"2nd masc. dual"},{"person":"2fd","arabic":"تَوْصُدَانِ","transliteration":"","english":"2nd fem. dual"},{"person":"2mp","arabic":"تَوْصُدُونَ","transliteration":"","english":"2nd masc. pl"},{"person":"2fp","arabic":"تَوْصُدْنَ","transliteration":"","english":"2nd fem. pl"},{"person":"1s","arabic":"أَوْصُدُ","transliteration":"","english":"1st singular"},{"person":"1p","arabic":"نَوْصُدُ","transliteration":"","english":"1st plural"}]},{"id":"وصد_I_amr","type":"amr","arabicName":"أَمْر","englishName":"Imperative (Amr)","color":"#ff6b6b","occurrences":0,"references":[],"conjugation":[{"person":"2ms","arabic":"ٱُوْصُدْ","transliteration":"","english":"2nd masc. sg"},{"person":"2fs","arabic":"ٱُوْصُدِي","transliteration":"","english":"2nd fem. sg"},{"person":"2md","arabic":"ٱُوْصُدَا","transliteration":"","english":"2nd masc. dual"},{"person":"2fd","arabic":"ٱُوْصُدَا","transliteration":"","english":"2nd fem. dual"},{"person":"2mp","arabic":"ٱُوْصُدُوا","transliteration":"","english":"2nd masc. pl"},{"person":"2fp","arabic":"ٱُوْصُدْنَ","transliteration":"","english":"2nd fem. pl"}]},{"id":"وصد_I_passive_madi","type":"passive_madi","arabicName":"مَاضِي مَجْهُول","englishName":"Pass. Past","color":"#c084fc","occurrences":0,"references":[],"conjugation":[{"person":"3ms","arabic":"وُصِدَ","transliteration":"","english":"3rd masc. sg"},{"person":"3fs","arabic":"وُصِدَتْ","transliteration":"","english":"3rd fem. sg"},{"person":"3md","arabic":"وُصِدَا","transliteration":"","english":"3rd masc. dual"},{"person":"3fd","arabic":"وُصِدَتَا","transliteration":"","english":"3rd fem. dual"},{"person":"3mp","arabic":"وُصِدُوا","transliteration":"","english":"3rd masc. pl"},{"person":"3fp","arabic":"وُصِدْنَ","transliteration":"","english":"3rd fem. pl"},{"person":"2ms","arabic":"وُصِدْتَ","transliteration":"","english":"2nd masc. sg"},{"person":"2fs","arabic":"وُصِدْتِ","transliteration":"","english":"2nd fem. sg"},{"person":"2md","arabic":"وُصِدْتُمَا","transliteration":"","english":"2nd masc. dual"},{"person":"2fd","arabic":"وُصِدْتُمَا","transliteration":"","english":"2nd fem. dual"},{"person":"2mp","arabic":"وُصِدْتُمْ","transliteration":"","english":"2nd masc. pl"},{"person":"2fp","arabic":"وُصِدْتُنَّ","transliteration":"","english":"2nd fem. pl"},{"person":"1s","arabic":"وُصِدْتُ","transliteration":"","english":"1st singular"},{"person":"1p","arabic":"وُصِدْنَا","transliteration":"","english":"1st plural"}]},{"id":"وصد_I_passive_mudari","type":"passive_mudari","arabicName":"مُضَارِع مَجْهُول","englishName":"Pass. Present","color":"#86efac","occurrences":0,"references":[],"conjugation":[{"person":"3ms","arabic":"يُوْصَدُ","transliteration":"","english":"3rd masc. sg"},{"person":"3fs","arabic":"تُوْصَدُ","transliteration":"","english":"3rd fem. sg"},{"person":"3md","arabic":"يُوْصَدَانِ","transliteration":"","english":"3rd masc. dual"},{"person":"3fd","arabic":"تُوْصَدَانِ","transliteration":"","english":"3rd fem. dual"},{"person":"3mp","arabic":"يُوْصَدُونَ","transliteration":"","english":"3rd masc. pl"},{"person":"3fp","arabic":"يُوْصَدْنَ","transliteration":"","english":"3rd fem. pl"},{"person":"2ms","arabic":"تُوْصَدُ","transliteration":"","english":"2nd masc. sg"},{"person":"2fs","arabic":"تُوْصَدِينَ","transliteration":"","english":"2nd fem. sg"},{"person":"2md","arabic":"تُوْصَدَانِ","transliteration":"","english":"2nd masc. dual"},{"person":"2fd","arabic":"تُوْصَدَانِ","transliteration":"","english":"2nd fem. dual"},{"person":"2mp","arabic":"تُوْصَدُونَ","transliteration":"","english":"2nd masc. pl"},{"person":"2fp","arabic":"تُوْصَدْنَ","transliteration":"","english":"2nd fem. pl"},{"person":"1s","arabic":"أُوْصَدُ","transliteration":"","english":"1st singular"},{"person":"1p","arabic":"نُوْصَدُ","transliteration":"","english":"1st plural"}]}],"formIDerivDone":true}],"totalFreq":3,"enriched":false,"allReferences":["18:18","90:20","104:8"],"validationDone":true,"isVerb":true}